<?xml version="1.0" encoding="UTF-8"?>
<apelonDtsConfigFile>
	<connectionInfo>
		<host>dev-db.further.utah.edu</host>
		<port>1521</port>
		<dbName>further</dbName>	
		<user>dts</user>	
	</connectionInfo>
	<supportedCodeSystems> <!--  code systems to which OpenCDS concepts are mapped with associations and subsets -->
		<supportedCodeSystem>2.16.840.1.113883.6.103</supportedCodeSystem> <!--  ICD-9-CM (diagnosis codes) -->
		<supportedCodeSystem>2.16.840.1.113883.6.104</supportedCodeSystem> <!--  ICD-9-CM (procedure codes) -->
		<supportedCodeSystem>2.16.840.1.113883.6.12</supportedCodeSystem> <!--  CPT -->
		<supportedCodeSystem>2.16.840.1.113883.5</supportedCodeSystem> <!--  HL7 -->
		<supportedCodeSystem>2.16.840.1.113883.6.1</supportedCodeSystem> <!--  LOINC -->
		<supportedCodeSystem>2.16.840.1.113883.6.96</supportedCodeSystem> <!--  SNOMED CT -->
	</supportedCodeSystems>
</apelonDtsConfigFile>
